gwf/__init__.py
gwf/cli.py
gwf/compat.py
gwf/conf.py
gwf/core.py
gwf/exceptions.py
gwf/filtering.py
gwf/utils.py
gwf/workflow.py
gwf/backends/__init__.py
gwf/backends/base.py
gwf/backends/exceptions.py
gwf/backends/local.py
gwf/backends/logmanager.py
gwf/backends/sge.py
gwf/backends/slurm.py
gwf/backends/testing.py
gwf/backends/utils.py
gwf/plugins/__init__.py
gwf/plugins/cancel.py
gwf/plugins/clean.py
gwf/plugins/config.py
gwf/plugins/info.py
gwf/plugins/init.py
gwf/plugins/logs.py
gwf/plugins/run.py
gwf/plugins/status.py
gwf/plugins/touch.py
gwf/plugins/workers.py
gwf-1.7.2.dist-info/LICENSE
gwf-1.7.2.dist-info/METADATA
gwf-1.7.2.dist-info/WHEEL
gwf-1.7.2.dist-info/entry_points.txt
gwf-1.7.2.dist-info/top_level.txt
gwf-1.7.2.dist-info/RECORD
