Metadata-Version: 2.1
Name: gwf
Version: 1.7.2
Summary: A flexible, pragmatic workflow tool.
Home-page: https://gwf.app/
Author: Dan Søndergaard
Author-email: das@birc.au.dk
License: UNKNOWN
Project-URL: Issues, https://github.com/gwforg/gwf/issues
Project-URL: Source code, https://github.com/gwforg/gwf
Platform: UNKNOWN
Classifier: Development Status :: 5 - Production/Stable
Classifier: Environment :: Console
Classifier: Operating System :: OS Independent
Classifier: Topic :: Utilities
Classifier: Topic :: System :: Distributed Computing
Classifier: Intended Audience :: Science/Research
Classifier: Programming Language :: Python
Classifier: Programming Language :: Python :: 3
Classifier: Intended Audience :: Science/Research
Classifier: License :: OSI Approved :: GNU General Public License v3 (GPLv3)
Requires-Python: >=3.5
Requires-Dist: click
Requires-Dist: click-plugins
